catex/__init__.py
catex/cli.py
catex/constants.py
catex/core.py
catex/version.py
CaTeX-0.0.10.dist-info/DESCRIPTION.rst
CaTeX-0.0.10.dist-info/entry_points.txt
CaTeX-0.0.10.dist-info/METADATA
CaTeX-0.0.10.dist-info/metadata.json
CaTeX-0.0.10.dist-info/RECORD
CaTeX-0.0.10.dist-info/top_level.txt
CaTeX-0.0.10.dist-info/WHEEL
