Metadata-Version: 2.0
Name: CaTeX
Version: 0.0.10
Summary: Concatenates LateX documents.
Home-page: https://github.com/Alexis-benoist/catex
Author: Alexis Benoist
Author-email: alexis@benoist.it
License: Apache License 2.0
Keywords: latex
Platform: UNKNOWN
Classifier: Development Status :: 4 - Beta
Classifier: Programming Language :: Python :: 2
Classifier: Programming Language :: Python :: 2.7
Classifier: Programming Language :: Python :: 3
Classifier: Programming Language :: Python :: 3.3
Classifier: Programming Language :: Python :: 3.4
Classifier: Programming Language :: Python :: 3.5
Classifier: Intended Audience :: Science/Research
Classifier: Topic :: Scientific/Engineering
Classifier: Topic :: Printing
Classifier: Topic :: Text Processing :: General
Classifier: Topic :: Text Processing :: Markup :: LaTeX
Requires-Dist: click (==6.6)
Requires-Dist: latex (==0.6.2)
